torch_pfaffian/__init__.py
torch_pfaffian/__main__.py
torch_pfaffian/utils.py
torch_pfaffian/strategies/__init__.py
torch_pfaffian/strategies/pfaffian_block_det.py
torch_pfaffian/strategies/pfaffian_fdbpf.py
torch_pfaffian/strategies/strategy.py
torchpfaffian-0.0.0.dist-info/LICENSE
torchpfaffian-0.0.0.dist-info/METADATA
torchpfaffian-0.0.0.dist-info/WHEEL
torchpfaffian-0.0.0.dist-info/top_level.txt
torchpfaffian-0.0.0.dist-info/RECORD
