Metadata-Version: 2.2
Name: TorchPfaffian
Version: 0.0.0
Author-email: Jérémie Gince <gincejeremie@gmail.com>
Classifier: Development Status :: 3 - Alpha
Classifier: Intended Audience :: Science/Research
Classifier: License :: OSI Approved :: Apache Software License
Classifier: Programming Language :: Python :: 3
Classifier: Programming Language :: Python :: 3.10
Classifier: Topic :: Scientific/Engineering
Classifier: Topic :: Software Development :: Libraries :: Python Modules
Classifier: Operating System :: OS Independent
Requires-Python: >=3.8
License-File: LICENSE
Requires-Dist: numpy>=1.23.0
Requires-Dist: setuptools>=57.0.0
Requires-Dist: torch
Requires-Dist: numpy
Dynamic: description
Dynamic: description-content-type
Dynamic: requires-python
